{"$schema":"https://json-schema.org/draft/2020-12/schema","$id":"https://github.com/polytomic/app/services/polytomic/backend/polytomic_metadata/connection-conf","properties":{"auth_mode":{"type":"string","enum":[{"value":"personal_api_key","label":"Personal API Key"},{"value":"partner_api_key","label":"Partner API Key"}],"title":"Authentication Method","description":"Type of API key to use for authentication","default":"personal_api_key","examples":["personal_api_key"]},"personal_api_key":{"type":"string","title":"Personal API Key","description":"Your personal API key from Polytomic settings","sensitive":true},"connected_user":{"type":"string","title":"Connected user","readOnly":true,"readonly":true},"connected_org":{"type":"string","title":"Connected organization","readOnly":true,"readonly":true},"partner_api_key":{"type":"string","title":"Partner API Key","description":"Partner API key provided by Polytomic","sensitive":true},"deployment_api_key":{"type":"string","title":"Deployment API Key","sensitive":true}},"type":"object","required":["auth_mode"]}
